control_unint.v
module control_unit(
    input [6:0] opcode,
    input [2:0] funct3,
    input [6:0] funct7,
    input zero,
    output mem2reg,
    output memwrite,
    output alusrc,
    output regwrite,
    output [3:0] aluctl,
    output branch,
    output is_lui,
    output is_jal,
    output is_jalr
    );
    // Definição dos opcodes (conforme ISA RISC-V)
    localparam R_TYPE    = 7'b0110011;  // ADD
    localparam I_TYPE    = 7'b0010011;  // ADDI
    localparam BRANCH    = 7'b1100011;  // BEQ

    localparam JAL = 7'b1101111;
    localparam JALR = 7'b1100111;
    localparam LUI = 7'b0110111;

    
    // Detecção dos tipos de instrução
    wire is_rtype = (opcode == R_TYPE);
    wire is_itype = (opcode == I_TYPE);
    wire is_branch = (opcode == BRANCH);

    assign is_jal = (opcode == JAL);
    assign is_jalr = (opcode == JALR);
    assign is_lui = (opcode == LUI);
    
    // Sinais de controle
    assign branch   = is_branch;
    assign mem2reg  = 1'b0;        
    assign memwrite = 1'b0;       
    assign alusrc   = is_itype | is_jalr | is_lui;  
    assign regwrite = is_rtype | is_itype | is_jal | is_jalr | is_lui;  
    
    assign aluctl = (is_branch | is_jalr | is_lui) ? 4'b0110 : 4'b0010;
    

endmodule

fluxo_dados.v
// 15484395 Pedro Origuela Porto
// os modulos da alu e do registerfile ja estão neste arquivo

module alu

  #(parameter W = 32)

(

  input  [3:0]   ALUctl,

  input  [W-1:0] A, B,
  input          rst,
  output [W-1:0] ALUout,

  output zero

);


assign ALUout = (ALUctl == 4'b0000) ? A & B : 
                  (ALUctl == 4'b0001) ? A | B : 
                  (ALUctl == 4'b0010) ? A + B : 
                  (ALUctl == 4'b0110) ? A - B :
                  (ALUctl == 4'b0111) ? {W{A < B}} :
                  ~(A | B);

assign zero = (ALUout == 0) ? 1'b1 : 1'b0;

endmodule

module registerfile

  #(parameter W = 32)

(

  input  [4  :0] Read1, Read2, WriteReg,

  input  [W-1:0] WriteData,

  input  RegWrite, clk,

  output [W-1:0] Data1, Data2

);

  reg [W-1:0] registers [31:1];
  integer i;

  initial begin
  for ( i = 1; i < 32; i = i + 1)
    registers[i] = 0;
end

  assign Data1 = (Read1 == 5'b00000) ? 0 : registers[Read1];

  assign Data2 = (Read2 == 5'b00000) ? 0 : registers[Read2];

  always @(posedge clk) begin
    if (RegWrite & WriteReg != 0)
      registers[WriteReg] <= WriteData;
  end

endmodule

module instruction_memory 
  #(parameter W = 32,
    parameter IFILE = "rom_hex.mem")
(
  input [W-1:0] addr,
  input CS, OE, regwrite,
  output reg [31:0] out
);

  reg [7:0] data[1023:0];  
  wire [W-1:0] word_addr = addr >> 2;
  integer i;
  
  initial begin
    // Inicializa a memória com zeros
    for (i = 0; i < 1024; i = i + 1)
      data[i] = 8'h0;
    
    // Carrega o arquivo ROM
    $readmemh(IFILE, data);
  end

  always @(addr, CS, OE)
    if (OE==1'b1) begin
            out = {data[word_addr*4], data[word_addr*4+1], 
             data[word_addr*4+2], data[word_addr*4+3]};
    end
    else begin
      out = 32'bz;
    end
endmodule


module imm_gen(
  input [31:0] instruction,  
  output reg [31:0] imm_out
);
  wire [6:0] opcode = instruction[6:0];


  always @(*) begin
    case (opcode)
      7'b1100111:
        imm_out = {{20{instruction[31]}}, instruction[31:20]};
      7'b0010011: // ADDI (tipo I)
        imm_out = {{20{instruction[31]}}, instruction[31:20]};
      7'b1100011: // BEQ (tipo B)
        imm_out = {{19{instruction[31]}}, instruction[31], instruction[7], instruction[30:25], instruction[11:8], 1'b0};
      7'b1101111: // JAL (tipo J)
      imm_out = {{11{instruction[31]}}, instruction[31], instruction[19:12], instruction[20], instruction[30:21], 1'b0};
      7'b0110111: //LUI
      imm_out = {instruction[31:12], 12'b0};
      default:
        imm_out = 32'b0;
    endcase
  end
endmodule

module DataMemory
  #(parameter W = 32)
(
  input [W-1:0] addr,
  input [W-1:0] data_in,
  input memwrite, memread, clk,
  output reg [W-1:0] data_out
);

  reg [W-1:0] memory[31:0];

  always @(posedge clk) begin
    if (memwrite)
      memory[addr] <= data_in;
    if (memread)
      data_out <= memory[addr];
  end
endmodule


module datapath
  #(parameter W = 32,
    parameter IFILE = "rom_hex.mem")
(
  input              clk,
  input              rst,
  input              branch,
  input              is_lui,
  input              is_jal,
  input              is_jalr,
  input              mem2reg,
  input              memwrite,
  input              alusrc,
  input              regwrite,
  input     [3:0]    aluctl,
  output             zero,
  output    [W-1:0]  instruction,
  output reg  [W-1:0]  pc
);


  wire [W-1:0] WriteData;
  wire [W-1:0] imm, next_pc, alu_out, rd1, rd2, memout;
  wire [2:0] pcsrc = branch & zero ? 3'b001 : 
                    is_jal ? 3'b010 :
                    is_jalr ? 3'b011 :
                    is_lui ? 3'b100 :
                    3'b000;

  instruction_memory #(.W(W), .IFILE(IFILE)) im0 (
    .addr(pc),
    .CS(1'b1),
    .OE(1'b1),
    .regwrite(regwrite),
    .out(instruction)
  );

  imm_gen ig0 (
    .instruction(instruction),
    .imm_out(imm)
  );

  registerfile #(.W(W)) rf0 (
    .Read1(instruction[19:15]),
    .Read2(instruction[24:20]),
    .WriteReg(instruction[11:7]),
    .WriteData(WriteData),
    .RegWrite(regwrite),
    .clk(clk),
    .Data1(rd1),
    .Data2(rd2)
  );

  always @(posedge clk or posedge rst) begin
    if (rst) begin
      pc <= 0;
    end else if (pcsrc == 1 || pcsrc == 2) begin
      pc <= pc + imm; 
    end else if (pcsrc ==3) begin
      pc <= (rd1 + imm) & ~1; // JALR: rs1 + imm com bit 0 forçado para 0
    end
    else begin
      pc <= pc + 4;
    end
  end


  wire [W-1:0] alu_src2 = alusrc ? imm : rd2;
  alu ula0 (
    .A(rd1),
    .B(alu_src2),
    .ALUctl(aluctl),
    .ALUout(alu_out),
    .zero(zero)
  );

  DataMemory #(.W(W)) dm0 (
    .addr(alu_out),
    .data_in(rd2),
    .memwrite(memwrite),
    .memread(mem2reg),
    .clk(clk),
    .data_out(memout)
  );

  assign WriteData = is_lui ? imm : 
                    (is_jal || is_jalr) ? pc + 4 :
                    mem2reg ? memout : alu_out;
endmodule

entrega_sd/poliriscv_sc.v
module poliriscv_sc #(
    parameter instructions = 256,
    parameter datawords = 1024,
    parameter IFILE = "rom_hex.mem"
)(
    input clk,
    input rst
);

    // Declaração dos sinais combinatórios
    wire mem2reg;
    wire memwrite;
    wire alusrc;
    wire regwrite;
    wire is_jal;
    wire is_jalr;
    wire is_lui;
    wire [3:0] aluctl;
    wire pcsrc;
    wire zero_comb;
    wire branch_comb;
    
    // Registradores para zero e branch

    wire [31:0] pc;
    wire [31:0] instruction;
    

    datapath #(
        .W(32)
    ) datapath0 (
        .clk(clk),
        .branch(branch_comb),
        .mem2reg(mem2reg),
        .memwrite(memwrite),
        .alusrc(alusrc),
        .regwrite(regwrite),
        .aluctl(aluctl),
        .rst(rst),
        .zero(zero_comb),  // Agora conectamos ao sinal combinatório
        .instruction(instruction),
        .pc(pc),
        .is_jal(is_jal),
        .is_jalr(is_jalr),
        .is_lui(is_lui)
    );

    control_unit control_unit0 (
        .opcode(instruction[6:0]),
        .funct3(instruction[14:12]),
        .funct7(instruction[31:25]),
        .branch(branch_comb),  // Agora conectamos ao sinal combinatório
        .mem2reg(mem2reg),
        .memwrite(memwrite),
        .zero(zero_comb),
        .alusrc(alusrc),
        .regwrite(regwrite),
        .aluctl(aluctl),
        .is_jal(is_jal),
        .is_jalr(is_jalr),
        .is_lui(is_lui)
    );

endmodule

poliriscv_sc_tb.v
`timescale 1ns/1ps
module poliriscv_sc_tb;

    localparam CLKP = 10;

    reg clk, rst;

    initial begin
        clk = 1'b0;
        forever
            #(CLKP/2) clk = ~clk;
    end

    integer i; // Contador de ciclos
    integer j; // Para iterar pela memória
    
    initial begin
        $dumpfile("polriscv_sc_tb.vcd");
        $dumpvars(0, riscv);
        
        // Dump da memória de instruções
        $display("\n=== CONTEÚDO DA MEMÓRIA DE INSTRUÇÕES ===");
        $display("Endereço\tInstrução (hex)");
        for (j = 0; j < 64; j = j + 1) begin
            $display("0x%h\t0x%h", j*4, riscv.datapath0.im0.data[j]);
        end
        
        // Reset inicial
        rst = 1'b1;
        #(CLKP) rst = 1'b0;
        
        // Cabeçalho
        $display("\n=== Iniciando simulação do RISC-V por 100 ciclos ===");
        $display("Ciclo\tPC\t\tInstrução\t\tZero\tBranch\tPCSrc\ta0\t\ta2\t\ta3\t\ta4\t\ta5");
        
        // Executa por até 100 ciclos
        for (i = 0; i < 100; i = i + 1) begin
            // Espera um ciclo de clock completo
            #(CLKP);
            
            // Mostra informações do estado atual
            $display("%0d\t0x%h\t0x%h\t%b\t%b\t%b\t0x%h\t0x%h\t0x%h\t0x%h\t0x%h", 
                    i, 
                    riscv.pc, 
                    riscv.instruction,
                    riscv.zero_comb,
                    riscv.branch_comb,
                    riscv.pcsrc,
                    riscv.datapath0.rf0.registers[2], // a0 (x10)
                    riscv.datapath0.rf0.registers[3], // a2 (x12)
                    riscv.datapath0.rf0.registers[5], // a3 (x13)
                    riscv.datapath0.rf0.registers[6], // a4 (x14)
                    riscv.datapath0.rf0.registers[7]  // a5 (x15)
                    );
        end
        
        // Mostra informações finais
        $display("\n=== Fim da simulação após %0d ciclos ===", i);
        $display("PC final = 0x%h", riscv.pc);
        $display("Valores finais dos registradores:");
        $display("a0 (2) = 0x%h", riscv.datapath0.rf0.registers[2]);
        $display("a2 (3) = 0x%h", riscv.datapath0.rf0.registers[3]);
        $display("a3 (5) = 0x%h", riscv.datapath0.rf0.registers[5]);
        $display("a4 (6) = 0x%h", riscv.datapath0.rf0.registers[6]);
        $display("a5 (7) = 0x%h", riscv.datapath0.rf0.registers[7]);
        
        $finish;
    end

    poliriscv_sc #(.instructions(256), .datawords(1024), .IFILE("rom_hex.mem"))
    riscv (.clk(clk), .rst(rst));

endmodule

polriscv_sc_tb.vcd
$date
	Sat Jun  7 17:35:29 2025
$end
$version
	Icarus Verilog
$end
$timescale
	1ps
$end
$scope module poliriscv_sc_tb $end
$scope module riscv $end
$var wire 1 ! clk $end
$var wire 1 " mem2reg $end
$var wire 1 # memwrite $end
$var wire 1 $ pcsrc $end
$var wire 1 % rst $end
$var wire 1 & zero_comb $end
$var wire 1 ' regwrite $end
$var wire 32 ( pc [31:0] $end
$var wire 1 ) is_lui $end
$var wire 1 * is_jalr $end
$var wire 1 + is_jal $end
$var wire 32 , instruction [31:0] $end
$var wire 1 - branch_comb $end
$var wire 1 . alusrc $end
$var wire 4 / aluctl [3:0] $end
$var parameter 88 0 IFILE $end
$var parameter 32 1 datawords $end
$var parameter 32 2 instructions $end
$scope module control_unit0 $end
$var wire 1 . alusrc $end
$var wire 1 - branch $end
$var wire 3 3 funct3 [2:0] $end
$var wire 7 4 funct7 [6:0] $end
$var wire 1 " mem2reg $end
$var wire 1 # memwrite $end
$var wire 7 5 opcode [6:0] $end
$var wire 1 ' regwrite $end
$var wire 1 & zero $end
$var wire 1 6 is_rtype $end
$var wire 1 ) is_lui $end
$var wire 1 * is_jalr $end
$var wire 1 + is_jal $end
$var wire 1 7 is_itype $end
$var wire 1 8 is_branch $end
$var wire 4 9 aluctl [3:0] $end
$var parameter 7 : BRANCH $end
$var parameter 7 ; I_TYPE $end
$var parameter 7 < JAL $end
$var parameter 7 = JALR $end
$var parameter 7 > LUI $end
$var parameter 7 ? R_TYPE $end
$upscope $end
$scope module datapath0 $end
$var wire 4 @ aluctl [3:0] $end
$var wire 1 . alusrc $end
$var wire 1 - branch $end
$var wire 1 ! clk $end
$var wire 1 + is_jal $end
$var wire 1 * is_jalr $end
$var wire 1 ) is_lui $end
$var wire 1 " mem2reg $end
$var wire 1 # memwrite $end
$var wire 1 ' regwrite $end
$var wire 1 % rst $end
$var wire 1 & zero $end
$var wire 32 A rd2 [31:0] $end
$var wire 32 B rd1 [31:0] $end
$var wire 3 C pcsrc [2:0] $end
$var wire 32 D memout [31:0] $end
$var wire 32 E instruction [31:0] $end
$var wire 32 F imm [31:0] $end
$var wire 32 G alu_src2 [31:0] $end
$var wire 32 H alu_out [31:0] $end
$var wire 32 I WriteData [31:0] $end
$var parameter 88 J IFILE $end
$var parameter 32 K W $end
$var reg 32 L pc [31:0] $end
$scope module dm0 $end
$var wire 1 ! clk $end
$var wire 1 " memread $end
$var wire 1 # memwrite $end
$var wire 32 M data_in [31:0] $end
$var wire 32 N addr [31:0] $end
$var parameter 32 O W $end
$var reg 32 P data_out [31:0] $end
$upscope $end
$scope module ig0 $end
$var wire 7 Q opcode [6:0] $end
$var wire 32 R instruction [31:0] $end
$var reg 32 S imm_out [31:0] $end
$upscope $end
$scope module im0 $end
$var wire 1 T CS $end
$var wire 1 U OE $end
$var wire 32 V addr [31:0] $end
$var wire 1 ' regwrite $end
$var wire 32 W word_addr [31:0] $end
$var parameter 88 X IFILE $end
$var parameter 32 Y W $end
$var reg 32 Z out [31:0] $end
$var integer 32 [ i [31:0] $end
$upscope $end
$scope module rf0 $end
$var wire 5 \ Read1 [4:0] $end
$var wire 5 ] Read2 [4:0] $end
$var wire 1 ' RegWrite $end
$var wire 32 ^ WriteData [31:0] $end
$var wire 5 _ WriteReg [4:0] $end
$var wire 1 ! clk $end
$var wire 32 ` Data2 [31:0] $end
$var wire 32 a Data1 [31:0] $end
$var parameter 32 b W $end
$var integer 32 c i [31:0] $end
$upscope $end
$scope module ula0 $end
$var wire 32 d A [31:0] $end
$var wire 4 e ALUctl [3:0] $end
$var wire 32 f B [31:0] $end
$var wire 1 g rst $end
$var wire 1 & zero $end
$var wire 32 h ALUout [31:0] $end
$var parameter 32 i W $end
$upscope $end
$upscope $end
$upscope $end
$upscope $end
$enddefinitions $end
$comment Show the parameter values. $end
$dumpall
b100000 i
b100000 b
b100000 Y
b111001001101111011011010101111101101000011001010111100000101110011011010110010101101101 X
b100000 O
b100000 K
b111001001101111011011010101111101101000011001010111100000101110011011010110010101101101 J
b110011 ?
b110111 >
b1100111 =
b1101111 <
b10011 ;
b1100011 :
b100000000 2
b10000000000 1
b111001001101111011011010101111101101000011001010111100000101110011011010110010101101101 0
$end
#0
$dumpvars
b11101101110010111011000000000000 h
zg
b10010001101000101000000000000 f
b110 e
b0 d
b100000 c
b0 a
b0 `
b101 _
b10010001101000101000000000000 ^
b11 ]
b1000 \
b10000000000 [
b10010001101000101001010110111 Z
b0 W
b0 V
1U
1T
b10010001101000101000000000000 S
b10010001101000101001010110111 R
b110111 Q
bx P
b11101101110010111011000000000000 N
b0 M
b0 L
b10010001101000101000000000000 I
b11101101110010111011000000000000 H
b10010001101000101000000000000 G
b10010001101000101000000000000 F
b10010001101000101001010110111 E
bx D
b100 C
b0 B
b0 A
b110 @
b110 9
08
07
06
b110111 5
b1001 4
b101 3
b110 /
1.
0-
b10010001101000101001010110111 ,
0+
0*
1)
b0 (
1'
0&
1%
z$
0#
0"
0!
$end
#5000
1!
#10000
0!
0%
#15000
1&
b0 H
b0 N
b0 h
b10 C
b10 /
b10 9
b10 @
b10 e
1'
0.
b1000 I
b1000 ^
b0 G
b0 f
b1101111 Q
b110 _
b10000 ]
b0 \
b0 4
b0 3
1+
0)
b1101111 5
b10000 F
b10000 S
b1000000000000001101101111 ,
b1000000000000001101101111 E
b1000000000000001101101111 R
b1000000000000001101101111 Z
b1 W
b100 (
b100 L
b100 V
1!
#20000
0!
#25000
0&
b10010001101000101000000000000 H
b10010001101000101000000000000 N
b10010001101000101000000000000 h
1'
1.
b0 C
b10010001101000101000000000000 B
b10010001101000101000000000000 a
b10010001101000101000000000000 d
b10010001101000101000000000000 I
b10010001101000101000000000000 ^
b10011 Q
b10 _
b0 ]
b101 \
17
0+
b10011 5
b0 F
b0 S
b101000000100010011 ,
b101000000100010011 E
b101000000100010011 R
b101000000100010011 Z
b101 W
b10100 (
b10100 L
b10100 V
1!
#30000
0!
#35000
b1000 H
b1000 N
b1000 h
b11100 I
b11100 ^
b11 C
b110 /
b110 9
b110 @
b110 e
b1000 B
b1000 a
b1000 d
b1100111 Q
b11 _
b110 \
07
1*
b1100111 5
b110000000111100111 ,
b110000000111100111 E
b110000000111100111 R
b110000000111100111 Z
b110 W
b11000 (
b11000 L
b11000 V
1!
#40000
0!
#45000
b1 H
b1 N
b1 h
b0 C
b10 /
b10 9
b10 @
b10 e
1'
b0 B
b0 a
b0 d
b1 G
b1 f
b1 I
b1 ^
b10011 Q
b111 _
b1 ]
b0 \
17
0*
b10011 5
b1 F
b1 S
b100000000001110010011 ,
b100000000001110010011 E
b100000000001110010011 R
b100000000001110010011 Z
b10 W
b1000 (
b1000 L
b1000 V
1!
#50000
0!
#55000
b10 I
b10 ^
b10 H
b10 N
b10 h
b10010001101000101000000000000 A
b10010001101000101000000000000 M
b10010001101000101000000000000 `
b10 G
b10 f
b10 ]
b10 F
b10 S
b1000000000001110010011 ,
b1000000000001110010011 E
b1000000000001110010011 R
b1000000000001110010011 Z
b11 W
b1100 (
b1100 L
b1100 V
1!
#60000
0!
#65000
1&
b0 H
b0 N
b0 h
b10100 I
b10100 ^
0.
b10 C
b0 A
b0 M
b0 `
b0 G
b0 f
b1101111 Q
b0 _
b10000 ]
07
1+
b1101111 5
b10000 F
b10000 S
b1000000000000000001101111 ,
b1000000000000000001101111 E
b1000000000000000001101111 R
b1000000000000000001101111 Z
b100 W
b10000 (
b10000 L
b10000 V
1!
#70000
0!
#75000
b100100 I
b100100 ^
b0 ]
b0 F
b0 S
b1101111 ,
b1101111 E
b1101111 R
b1101111 Z
b1000 W
b100000 (
b100000 L
b100000 V
1!
