entrega_sd/control_unint.v
module control_unit(
    input [6:0] opcode,
    input [2:0] funct3,
    input [6:0] funct7,
    input zero,
    output mem2reg,
    output memwrite,
    output alusrc,
    output regwrite,
    output [3:0] aluctl,
    output branch,
    output is_lui,
    output is_jal,
    output is_jalr
    );
    // Definição dos opcodes (conforme ISA RISC-V)
    localparam R_TYPE    = 7'b0110011;  // ADD
    localparam I_TYPE    = 7'b0010011;  // ADDI
    localparam BRANCH    = 7'b1100011;  // BEQ

    localparam JAL = 7'b1101111;
    localparam JALR = 7'b1100111;
    localparam LUI = 7'b0110111;

    localparam ADD = 3'b000;
    localparam SUB = 3'b000;
    localparam XOR = 3'b100;
    localparam OR = 3'b110;
    localparam AND = 3'b111;
    localparam SHIFT_LL  = 3'b001;
    localparam SHIFT_RL = 3'b101;
    localparam SHIFT_RA = 3'b101;
    localparam SET_LTS = 3'b010; // signed
    localparam SET_LTU = 3'b011; // unsinged
    

    
    // Detecção dos tipos de instrução
    wire is_rtype = (opcode == R_TYPE);
    wire is_itype = (opcode == I_TYPE);
    wire is_branch = (opcode == BRANCH);

    assign is_jal = (opcode == JAL);
    assign is_jalr = (opcode == JALR);
    assign is_lui = (opcode == LUI);
    
    // Sinais de controle
    assign branch   = is_branch;
    assign mem2reg  = 1'b0;        
    assign memwrite = 1'b0;       
    assign alusrc   = is_itype | is_jalr | is_lui;  
    assign regwrite = is_rtype | is_itype | is_jal | is_jalr | is_lui;  
    

    // Sinais da alu
    wire is_add = ((funct3 == ADD) && (funct7 == 7'h00)) || ((funct3 == ADD) && is_itype); //
    wire is_sub = (funct3 == SUB) && (funct7 == 7'h20); //
    wire is_xor = (funct3 == XOR); 
    wire is_or = (funct3 == OR); //
    wire is_and = (funct3 == AND); //
    wire is_shift_ll = (funct3 == SHIFT_LL);
    wire is_shift_rl = (funct3 == SHIFT_RL) && (funct7 == 7'h00);
    wire is_shift_ra = (funct3 == SHIFT_RA) && (funct7 == 7'h20); // shift right arithmetic
    wire is_set_lts = (funct3 == SET_LTS);
    wire is_set_ltu = (funct3 == SET_LTU);

    assign aluctl = is_and ? 4'b0000 :
                    is_or ? 4'b0001 :
                    is_add ? 4'b0010 :
                    is_sub ? 4'b0011 :
                    is_set_ltu ? 4'b0100 :
                    is_set_lts ? 4'b0101 :
                    is_xor ? 4'b0110 :
                    is_shift_ll ? 4'b0111 :
                    is_shift_rl ? 4'b1000 :
                    is_shift_ra ? 4'b1001: 
                    4'bz; // shift right arithmetic 

endmodule

entrega_sd/fluxo_dados.v
// 15484395 Pedro Origuela Porto
// os modulos da alu e do registerfile ja estão neste arquivo

module alu

  #(parameter W = 32)

(

  input  [3:0]   ALUctl,

  input  [W-1:0] A, B,

  output [W-1:0] ALUout,

  output zero

);


assign ALUout = (ALUctl == 4'b0000) ? A & B : 
                  (ALUctl == 4'b0001) ? A | B : 
                  (ALUctl == 4'b0010) ? A + B : 
                  (ALUctl == 4'b0011) ? A - B :
                  (ALUctl == 4'b0100) ? {W{A < B}} :
                  (ALUctl == 4'b0101) ? {W{$signed(A) < $signed(B)}} : // Slt (set less than)
                  (ALUctl == 4'b0110) ? A ^ B :                     // XOR
                  (ALUctl == 4'b0111) ? A << B[4:0] :               // SLL (shift left logical)
                  (ALUctl == 4'b1000) ? A >> B[4:0] :               // SRL (shift right logical)
                  (ALUctl == 4'b1001) ? $signed($signed(A) >>> B[4:0]) : // SRA (shift right arithmetic)
                  A; 
assign zero = (ALUout == 0) ? 1'b1 : 1'b0;

endmodule

module registerfile

  #(parameter W = 32)

(

  input  [4  :0] Read1, Read2, WriteReg,

  input  [W-1:0] WriteData,

  input  RegWrite, clk,

  output [W-1:0] Data1, Data2

);

  reg [W-1:0] registers [31:1];
  integer i;

  initial begin
  for ( i = 1; i < 32; i = i + 1)
    registers[i] = 0;
end

  assign Data1 = (Read1 == 5'b00000) ? 0 : registers[Read1];

  assign Data2 = (Read2 == 5'b00000) ? 0 : registers[Read2];

  always @(posedge clk) begin
    if (RegWrite & WriteReg != 0)
      registers[WriteReg] <= WriteData;
  end

endmodule

module instruction_memory 
  #(parameter W = 32,
    parameter IFILE = "rom_hex.mem")
(
  input [W-1:0] addr,
  input CS, OE, regwrite,
  output reg [31:0] out
);

  reg [7:0] data[1023:0];  
  wire [W-1:0] word_addr = addr >> 2;
  integer i;
  
  initial begin
    // Inicializa a memória com zeros
    for (i = 0; i < 1024; i = i + 1)
      data[i] = 8'h0;
    
    // Carrega o arquivo ROM
    $readmemh(IFILE, data);
  end

  always @(addr, CS, OE)
    if (OE==1'b1) begin
            out = {data[word_addr*4], data[word_addr*4+1], 
             data[word_addr*4+2], data[word_addr*4+3]};
    end
    else begin
      out = 32'bz;
    end
endmodule


module imm_gen(
  input [31:0] instruction,  
  output reg [31:0] imm_out
);
  wire [6:0] opcode = instruction[6:0];


  always @(*) begin
    case (opcode)
      7'b1100111:
        imm_out = {{20{instruction[31]}}, instruction[31:20]};
      7'b0010011: // ADDI (tipo I)
        imm_out = {{20{instruction[31]}}, instruction[31:20]};
      7'b1100011: // BEQ (tipo B)
        imm_out = {{19{instruction[31]}}, instruction[31], instruction[7], instruction[30:25], instruction[11:8], 1'b0};
      7'b1101111: // JAL (tipo J)
      imm_out = {{11{instruction[31]}}, instruction[31], instruction[19:12], instruction[20], instruction[30:21], 1'b0};
      7'b0110111: //LUI
      imm_out = {instruction[31:12], 12'b0};
      default:
        imm_out = 32'b0;
    endcase
  end
endmodule

module DataMemory
  #(parameter W = 32)
(
  input [W-1:0] addr,
  input [W-1:0] data_in,
  input memwrite, memread, clk,
  output reg [W-1:0] data_out
);

  reg [W-1:0] memory[31:0];

  always @(posedge clk) begin
    if (memwrite)
      memory[addr] <= data_in;
    if (memread)
      data_out <= memory[addr];
  end
endmodule


module datapath
  #(parameter W = 32,
    parameter IFILE = "rom_hex.mem")
(
  input              clk,
  input              rst,
  input              branch,
  input              is_lui,
  input              is_jal,
  input              is_jalr,
  input              mem2reg,
  input              memwrite,
  input              alusrc,
  input              regwrite,
  input     [3:0]    aluctl,
  output             zero,
  output    [W-1:0]  instruction,
  output reg  [W-1:0]  pc
);


  wire [W-1:0] WriteData;
  wire [W-1:0] imm, next_pc, alu_out, rd1, rd2, memout;
  wire [2:0] pcsrc = branch & zero ? 3'b001 : 
                    is_jal ? 3'b010 :
                    is_jalr ? 3'b011 :
                    is_lui ? 3'b100 :
                    3'b000;

  instruction_memory #(.W(W), .IFILE(IFILE)) im0 (
    .addr(pc),
    .CS(1'b1),
    .OE(1'b1),
    .regwrite(regwrite),
    .out(instruction)
  );

  imm_gen ig0 (
    .instruction(instruction),
    .imm_out(imm)
  );

  registerfile #(.W(W)) rf0 (
    .Read1(instruction[19:15]),
    .Read2(instruction[24:20]),
    .WriteReg(instruction[11:7]),
    .WriteData(WriteData),
    .RegWrite(regwrite),
    .clk(clk),
    .Data1(rd1),
    .Data2(rd2)
  );

  always @(posedge clk or posedge rst) begin
    if (rst) begin
      pc <= 0;
    end else if (pcsrc == 1 || pcsrc == 2) begin
      pc <= pc + imm; 
    end else if (pcsrc ==3) begin
      pc <= (rd1 + imm) & ~1; // JALR: rs1 + imm com bit 0 forçado para 0
    end
    else begin
      pc <= pc + 4;
    end
  end


  wire [W-1:0] alu_src2 = alusrc ? imm : rd2;
  alu ula0 (
    .A(rd1),
    .B(alu_src2),
    .ALUctl(aluctl),
    .ALUout(alu_out),
    .zero(zero)
  );

  DataMemory #(.W(W)) dm0 (
    .addr(alu_out),
    .data_in(rd2),
    .memwrite(memwrite),
    .memread(mem2reg),
    .clk(clk),
    .data_out(memout)
  );

  assign WriteData = is_lui ? imm : 
                    (is_jal || is_jalr) ? pc + 4 :
                    mem2reg ? memout : alu_out;
endmodule

entrega_sd/poliriscv_sc.v
module poliriscv_sc #(
    parameter instructions = 256,
    parameter datawords = 1024,
    parameter IFILE = "rom_hex.mem"
)(
    input clk,
    input rst
);

    // Declaração dos sinais combinatórios
    wire mem2reg;
    wire memwrite;
    wire alusrc;
    wire regwrite;
    wire is_jal;
    wire is_jalr;
    wire is_lui;
    wire [3:0] aluctl;
    wire pcsrc;
    wire zero_comb;
    wire branch_comb;
    
    // Registradores para zero e branch

    wire [31:0] pc;
    wire [31:0] instruction;
    

    datapath #(
        .W(32)
    ) datapath0 (
        .clk(clk),
        .branch(branch_comb),
        .mem2reg(mem2reg),
        .memwrite(memwrite),
        .alusrc(alusrc),
        .regwrite(regwrite),
        .aluctl(aluctl),
        .rst(rst),
        .zero(zero_comb),  // Agora conectamos ao sinal combinatório
        .instruction(instruction),
        .pc(pc),
        .is_jal(is_jal),
        .is_jalr(is_jalr),
        .is_lui(is_lui)
    );

    control_unit control_unit0 (
        .opcode(instruction[6:0]),
        .funct3(instruction[14:12]),
        .funct7(instruction[31:25]),
        .branch(branch_comb),  // Agora conectamos ao sinal combinatório
        .mem2reg(mem2reg),
        .memwrite(memwrite),
        .zero(zero_comb),
        .alusrc(alusrc),
        .regwrite(regwrite),
        .aluctl(aluctl),
        .is_jal(is_jal),
        .is_jalr(is_jalr),
        .is_lui(is_lui)
    );

endmodule

entrega_sd/poliriscv_sc_tb.v
`timescale 1ns/1ps

module poliriscv_tb();
    reg clk;
    reg rst;
    
    // Instancia o processador
    poliriscv_sc #(
        .instructions(256),
        .datawords(1024),
        .IFILE("test_program.mem")  // Arquivo que conterá nosso programa de teste
    ) dut (
        .clk(clk),
        .rst(rst)
    );
    
    // Acesso aos sinais internos para monitoramento
    wire [31:0] pc = dut.datapath0.pc;
    wire [31:0] instruction = dut.instruction;
    wire [31:0] alu_out = dut.datapath0.alu_out;
    wire [31:0] rd1 = dut.datapath0.rd1;
    wire [31:0] rd2 = dut.datapath0.rd2;
    wire [31:0] imm = dut.datapath0.imm;
    wire zero = dut.datapath0.zero;
    wire [3:0] aluctl = dut.aluctl;
    
    // Geração do clock
    initial begin
        clk = 0;
        forever #5 clk = ~clk;
    end
    
    // Monitoramento e verificação
    initial begin
        $display("Starting RISC-V Processor Test");
        $display("================================");
        
        // Inicializa o processador
        rst = 1;
        #10;
        rst = 0;
        
        // Espera alguns ciclos para as instruções executarem
        #500;
        
        // Verifica registradores específicos para confirmar resultados
        $display("Test Complete - Check register values in waveform viewer");
        
         // Verifica registradores específicos para confirmar resultados
        $display("Test Complete - Verificando os resultados esperados:");
        $display("x1 (Valor esperado 10): %h", dut.datapath0.rf0.registers[1]);
        $display("x2 (Valor esperado 5): %h", dut.datapath0.rf0.registers[2]);
        $display("x3 (Valor esperado -5 / 0xFFFFFFFB): %h", dut.datapath0.rf0.registers[3]);
        $display("x5 (ADD: Valor esperado 15): %h", dut.datapath0.rf0.registers[5]);
        $display("x6 (SUB: Valor esperado 5): %h", dut.datapath0.rf0.registers[6]);
        $display("x7 (AND: Valor esperado 0): %h", dut.datapath0.rf0.registers[7]);
        $display("x9 (XOR: Valor esperado 0xFA): %h", dut.datapath0.rf0.registers[9]);
        $display("x10 (SLL: Valor esperado 40): %d", dut.datapath0.rf0.registers[10]);
        $display("x11 (SRL: Valor esperado 0xF): %h", dut.datapath0.rf0.registers[11]);
        $display("x12 (SRA: Valor esperado -3): %d", dut.datapath0.rf0.registers[12]);
        $display("x13 (SLT: Valor esperado 1): %d", dut.datapath0.rf0.registers[13]);
        $display("x14 (SLTU: Valor esperado 0): %d", dut.datapath0.rf0.registers[14]);

        // Encerra a simulação
        $finish;
    end
    
    // Monitor para observar a execução de instruções
    always @(posedge clk) begin
        if (!rst) begin
            $display("Time: %0t, PC: %h, Instruction: %h", $time, pc, instruction);
            $display("ALU Control: %b, ALU Out: %h, Zero: %b", aluctl, alu_out, zero);
            $display("Register values - RD1: %h, RD2: %h", dut.datapath0.rf0.registers[1], dut.datapath0.rf0.registers[2]);
            $display("--------------------------------------------------");
        end
    end
    
    // Cria arquivo para visualizar forma de onda
    initial begin
        $dumpfile("poliriscv_tb.vcd");
        $dumpvars(0, poliriscv_tb);
    end

endmodule

entrega_sd/poliriscv_tb.vcd
$date
	Fri Jun 13 13:04:42 2025
$end
$version
	Icarus Verilog
$end
$timescale
	1ps
$end
$scope module poliriscv_tb $end
$var wire 32 ! alu_out [31:0] $end
$var wire 4 " aluctl [3:0] $end
$var wire 32 # imm [31:0] $end
$var wire 32 $ instruction [31:0] $end
$var wire 32 % pc [31:0] $end
$var wire 32 & rd1 [31:0] $end
$var wire 32 ' rd2 [31:0] $end
$var wire 1 ( zero $end
$var reg 1 ) clk $end
$var reg 1 * rst $end
$scope module dut $end
$var wire 1 ) clk $end
$var wire 1 + mem2reg $end
$var wire 1 , memwrite $end
$var wire 1 * rst $end
$var wire 1 - zero_comb $end
$var wire 1 . regwrite $end
$var wire 32 / pc [31:0] $end
$var wire 1 0 is_lui $end
$var wire 1 1 is_jalr $end
$var wire 1 2 is_jal $end
$var wire 32 3 instruction [31:0] $end
$var wire 1 4 branch_comb $end
$var wire 1 5 alusrc $end
$var wire 4 6 aluctl [3:0] $end
$var parameter 128 7 IFILE $end
$var parameter 32 8 datawords $end
$var parameter 32 9 instructions $end
$scope module control_unit0 $end
$var wire 1 5 alusrc $end
$var wire 1 4 branch $end
$var wire 3 : funct3 [2:0] $end
$var wire 7 ; funct7 [6:0] $end
$var wire 1 < is_add $end
$var wire 1 = is_shift_ra $end
$var wire 1 > is_shift_rl $end
$var wire 1 ? is_sub $end
$var wire 1 + mem2reg $end
$var wire 1 , memwrite $end
$var wire 7 @ opcode [6:0] $end
$var wire 1 . regwrite $end
$var wire 1 - zero $end
$var wire 1 A is_xor $end
$var wire 1 B is_shift_ll $end
$var wire 1 C is_set_ltu $end
$var wire 1 D is_set_lts $end
$var wire 1 E is_rtype $end
$var wire 1 F is_or $end
$var wire 1 0 is_lui $end
$var wire 1 1 is_jalr $end
$var wire 1 2 is_jal $end
$var wire 1 G is_itype $end
$var wire 1 H is_branch $end
$var wire 1 I is_and $end
$var wire 4 J aluctl [3:0] $end
$var parameter 3 K ADD $end
$var parameter 3 L AND $end
$var parameter 7 M BRANCH $end
$var parameter 7 N I_TYPE $end
$var parameter 7 O JAL $end
$var parameter 7 P JALR $end
$var parameter 7 Q LUI $end
$var parameter 3 R OR $end
$var parameter 7 S R_TYPE $end
$var parameter 3 T SET_LTS $end
$var parameter 3 U SET_LTU $end
$var parameter 3 V SHIFT_LL $end
$var parameter 3 W SHIFT_RA $end
$var parameter 3 X SHIFT_RL $end
$var parameter 3 Y SUB $end
$var parameter 3 Z XOR $end
$upscope $end
$scope module datapath0 $end
$var wire 4 [ aluctl [3:0] $end
$var wire 1 5 alusrc $end
$var wire 1 4 branch $end
$var wire 1 ) clk $end
$var wire 1 2 is_jal $end
$var wire 1 1 is_jalr $end
$var wire 1 0 is_lui $end
$var wire 1 + mem2reg $end
$var wire 1 , memwrite $end
$var wire 1 . regwrite $end
$var wire 1 * rst $end
$var wire 1 - zero $end
$var wire 32 \ rd2 [31:0] $end
$var wire 32 ] rd1 [31:0] $end
$var wire 3 ^ pcsrc [2:0] $end
$var wire 32 _ memout [31:0] $end
$var wire 32 ` instruction [31:0] $end
$var wire 32 a imm [31:0] $end
$var wire 32 b alu_src2 [31:0] $end
$var wire 32 c alu_out [31:0] $end
$var wire 32 d WriteData [31:0] $end
$var parameter 88 e IFILE $end
$var parameter 32 f W $end
$var reg 32 g pc [31:0] $end
$scope module dm0 $end
$var wire 1 ) clk $end
$var wire 1 + memread $end
$var wire 1 , memwrite $end
$var wire 32 h data_in [31:0] $end
$var wire 32 i addr [31:0] $end
$var parameter 32 j W $end
$var reg 32 k data_out [31:0] $end
$upscope $end
$scope module ig0 $end
$var wire 7 l opcode [6:0] $end
$var wire 32 m instruction [31:0] $end
$var reg 32 n imm_out [31:0] $end
$upscope $end
$scope module im0 $end
$var wire 1 o CS $end
$var wire 1 p OE $end
$var wire 32 q addr [31:0] $end
$var wire 1 . regwrite $end
$var wire 32 r word_addr [31:0] $end
$var parameter 88 s IFILE $end
$var parameter 32 t W $end
$var reg 32 u out [31:0] $end
$var integer 32 v i [31:0] $end
$upscope $end
$scope module rf0 $end
$var wire 5 w Read1 [4:0] $end
$var wire 5 x Read2 [4:0] $end
$var wire 1 . RegWrite $end
$var wire 32 y WriteData [31:0] $end
$var wire 5 z WriteReg [4:0] $end
$var wire 1 ) clk $end
$var wire 32 { Data2 [31:0] $end
$var wire 32 | Data1 [31:0] $end
$var parameter 32 } W $end
$var integer 32 ~ i [31:0] $end
$upscope $end
$scope module ula0 $end
$var wire 32 !" A [31:0] $end
$var wire 4 "" ALUctl [3:0] $end
$var wire 32 #" B [31:0] $end
$var wire 1 - zero $end
$var wire 32 $" ALUout [31:0] $end
$var parameter 32 %" W $end
$upscope $end
$upscope $end
$upscope $end
$upscope $end
$enddefinitions $end
$comment Show the parameter values. $end
$dumpall
b100000 %"
b100000 }
b100000 t
b111001001101111011011010101111101101000011001010111100000101110011011010110010101101101 s
b100000 j
b100000 f
b111001001101111011011010101111101101000011001010111100000101110011011010110010101101101 e
b100 Z
b0 Y
b101 X
b101 W
b1 V
b11 U
b10 T
b110011 S
b110 R
b110111 Q
b1100111 P
b1101111 O
b10011 N
b1100011 M
b111 L
b0 K
b100000000 9
b10000000000 8
b1110100011001010111001101110100010111110111000001110010011011110110011101110010011000010110110100101110011011010110010101101101 7
$end
#0
$dumpvars
b1010 $"
b1010 #"
b10 ""
b0 !"
b100000 ~
b0 |
b0 {
b1 z
b1010 y
b1010 x
b0 w
b10000000000 v
b101000000000000010010011 u
b0 r
b0 q
1p
1o
b1010 n
b101000000000000010010011 m
b10011 l
bx k
b1010 i
b0 h
b0 g
b1010 d
b1010 c
b1010 b
b1010 a
b101000000000000010010011 `
bx _
b0 ^
b0 ]
b0 \
b10 [
b10 J
0I
0H
1G
0F
0E
0D
0C
0B
0A
b10011 @
0?
0>
0=
1<
b0 ;
b0 :
b10 6
15
04
b101000000000000010010011 3
02
01
00
b0 /
1.
0-
0,
0+
1*
0)
0(
b0 '
b0 &
b0 %
b101000000000000010010011 $
b1010 #
b10 "
b1010 !
$end
#5000
1)
#10000
0)
0*
#15000
b101 d
b101 y
b101 !
b101 c
b101 i
b101 $"
b101 b
b101 #"
b10 z
b101 x
b101 #
b101 a
b101 n
b10100000000000100010011 $
b10100000000000100010011 3
b10100000000000100010011 `
b10100000000000100010011 m
b10100000000000100010011 u
b1 r
b100 %
b100 /
b100 g
b100 q
1)
#20000
0)
#25000
b11111111111111111111111111111011 d
b11111111111111111111111111111011 y
b11111111111111111111111111111011 !
b11111111111111111111111111111011 c
b11111111111111111111111111111011 i
b11111111111111111111111111111011 $"
b11111111111111111111111111111011 b
b11111111111111111111111111111011 #"
b11 z
b11011 x
b1111111 ;
b11111111111111111111111111111011 #
b11111111111111111111111111111011 a
b11111111111111111111111111111011 n
b11111111101100000000000110010011 $
b11111111101100000000000110010011 3
b11111111101100000000000110010011 `
b11111111101100000000000110010011 m
b11111111101100000000000110010011 u
b10 r
b1000 %
b1000 /
b1000 g
b1000 q
1)
#30000
0)
#35000
b11110000 d
b11110000 y
b11110000 !
b11110000 c
b11110000 i
b11110000 $"
b11110000 b
b11110000 #"
b100 z
b10000 x
b111 ;
b11110000 #
b11110000 a
b11110000 n
b1111000000000000001000010011 $
b1111000000000000001000010011 3
b1111000000000000001000010011 `
b1111000000000000001000010011 m
b1111000000000000001000010011 u
b11 r
b1100 %
b1100 /
b1100 g
b1100 q
1)
#40000
0)
#45000
b1111 d
b1111 y
b1111 !
b1111 c
b1111 i
b1111 $"
05
b101 '
b101 \
b101 h
b101 {
b1010 &
b1010 ]
b1010 |
b1010 !"
b101 b
b101 #"
b110011 l
b101 z
b10 x
b1 w
b0 ;
1E
0G
b110011 @
b0 #
b0 a
b0 n
b1000001000001010110011 $
b1000001000001010110011 3
b1000001000001010110011 `
b1000001000001010110011 m
b1000001000001010110011 u
b100 r
b10000 %
b10000 /
b10000 g
b10000 q
1)
#50000
0)
#55000
b101 d
b101 y
b101 !
b101 c
b101 i
b101 $"
b11 "
b11 6
b11 J
b11 [
b11 ""
0<
1?
b110 z
b100000 ;
b1000000001000001000001100110011 $
b1000000001000001000001100110011 3
b1000000001000001000001100110011 `
b1000000001000001000001100110011 m
b1000000001000001000001100110011 u
b101 r
b10100 %
b10100 /
b10100 g
b10100 q
1)
#60000
0)
#65000
b0 d
b0 y
1(
1-
b11110000 b
b11110000 #"
b0 !
b0 c
b0 i
b0 $"
b11110000 '
b11110000 \
b11110000 h
b11110000 {
0?
b0 "
b0 6
b0 J
b0 [
b0 ""
b111 z
b100 x
b0 ;
1I
b111 :
b10000001111001110110011 $
b10000001111001110110011 3
b10000001111001110110011 `
b10000001111001110110011 m
b10000001111001110110011 u
b110 r
b11000 %
b11000 /
b11000 g
b11000 q
1)
#70000
0)
#75000
b11111010 d
b11111010 y
0(
0-
b11111010 !
b11111010 c
b11111010 i
b11111010 $"
b1 "
b1 6
b1 J
b1 [
b1 ""
b1000 z
1F
0I
b110 :
b10000001110010000110011 $
b10000001110010000110011 3
b10000001110010000110011 `
b10000001110010000110011 m
b10000001110010000110011 u
b111 r
b11100 %
b11100 /
b11100 g
b11100 q
1)
#80000
0)
#85000
b11111010 d
b11111010 y
0(
0-
b11111010 !
b11111010 c
b11111010 i
b11111010 $"
b110 "
b110 6
b110 J
b110 [
b110 ""
b1001 z
1A
0F
b100 :
b10000001100010010110011 $
b10000001100010010110011 3
b10000001100010010110011 `
b10000001100010010110011 m
b10000001100010010110011 u
b1000 r
b100000 %
b100000 /
b100000 g
b100000 q
1)
#90000
0)
#95000
b101000 d
b101000 y
b101000 !
b101000 c
b101000 i
b101000 $"
b111 "
b111 6
b111 J
b111 [
b111 ""
b10 b
b10 #"
15
b10 #
b10 a
b10 n
b101 '
b101 \
b101 h
b101 {
b10011 l
b1010 z
b10 x
0A
1B
b1 :
0E
1G
b10011 @
b1000001001010100010011 $
b1000001001010100010011 3
b1000001001010100010011 `
b1000001001010100010011 m
b1000001001010100010011 u
b1001 r
b100100 %
b100100 /
b100100 g
b100100 q
1)
#100000
0)
#105000
b1111 d
b1111 y
0(
0-
b1111 !
b1111 c
b1111 i
b1111 $"
b1000 "
b1000 6
b1000 J
b1000 [
b1000 ""
b11110000 '
b11110000 \
b11110000 h
b11110000 {
b11110000 &
b11110000 ]
b11110000 |
b11110000 !"
1>
b100 b
b100 #"
b1011 z
b100 x
b100 w
0B
b101 :
b100 #
b100 a
b100 n
b10000100101010110010011 $
b10000100101010110010011 3
b10000100101010110010011 `
b10000100101010110010011 m
b10000100101010110010011 u
b1010 r
b101000 %
b101000 /
b101000 g
b101000 q
1)
#110000
0)
#115000
b11111111111111111111111111111101 d
b11111111111111111111111111111101 y
b11111111111111111111111111111101 !
b11111111111111111111111111111101 c
b11111111111111111111111111111101 i
b11111111111111111111111111111101 $"
b1001 "
b1001 6
b1001 J
b1001 [
b1001 ""
b1010 '
b1010 \
b1010 h
b1010 {
b11111111111111111111111111111011 &
b11111111111111111111111111111011 ]
b11111111111111111111111111111011 |
b11111111111111111111111111111011 !"
0>
1=
b10000000001 b
b10000000001 #"
b1100 z
b1 x
b11 w
b100000 ;
b10000000001 #
b10000000001 a
b10000000001 n
b1000000000100011101011000010011 $
b1000000000100011101011000010011 3
b1000000000100011101011000010011 `
b1000000000100011101011000010011 m
b1000000000100011101011000010011 u
b1011 r
b101100 %
b101100 /
b101100 g
b101100 q
1)
#120000
0)
#125000
b11111111111111111111111111111111 d
b11111111111111111111111111111111 y
b11111111111111111111111111111111 !
b11111111111111111111111111111111 c
b11111111111111111111111111111111 i
b11111111111111111111111111111111 $"
b101 "
b101 6
b101 J
b101 [
b101 ""
05
0=
b1010 b
b1010 #"
b110011 l
b1101 z
b0 ;
1D
b10 :
1E
0G
b110011 @
b0 #
b0 a
b0 n
b100011010011010110011 $
b100011010011010110011 3
b100011010011010110011 `
b100011010011010110011 m
b100011010011010110011 u
b1100 r
b110000 %
b110000 /
b110000 g
b110000 q
1)
#130000
0)
#135000
b0 d
b0 y
1(
1-
b0 !
b0 c
b0 i
b0 $"
b100 "
b100 6
b100 J
b100 [
b100 ""
b1110 z
0D
1C
b11 :
b100011011011100110011 $
b100011011011100110011 3
b100011011011100110011 `
b100011011011100110011 m
b100011011011100110011 u
b1101 r
b110100 %
b110100 /
b110100 g
b110100 q
1)
#140000
0)
#145000
1(
1-
b0 !
b0 c
b0 i
b0 $"
b10 "
b10 6
b10 J
b10 [
b10 ""
b111100 d
b111100 y
b0 b
b0 #"
1<
b10 ^
b0 '
b0 \
b0 h
b0 {
b0 &
b0 ]
b0 |
b0 !"
b1101111 l
b0 z
b0 x
b0 w
0C
b0 :
0E
12
b1101111 @
b1101111 $
b1101111 3
b1101111 `
b1101111 m
b1101111 u
b1110 r
b111000 %
b111000 /
b111000 g
b111000 q
1)
